<?xml version='1.0' encoding='UTF-8'?><dataroot><lista_paises_bing><codigo>prs-af</codigo><portugues>Afeganistão</portugues><ingles>Afghanistan</ingles><espanhol>Afganistán</espanhol></lista_paises_bing><lista_paises_bing><codigo>en-za</codigo><portugues>África do Sul</portugues><ingles>South Africa</ingles><espanhol>Sudáfrica</espanhol></lista_paises_bing><lista_paises_bing><codigo>sq-al</codigo><portugues>Albânia</portugues><ingles>Albania</ingles><espanhol>Albania</espanhol></lista_paises_bing><lista_paises_bing><codigo>de-de</codigo><portugues>Alemanha</portugues><ingles>Germany</ingles><espanhol>Alemania</espanhol></lista_paises_bing><lista_paises_bing><codigo>ca-ad</codigo><portugues>Andorra</portugues><ingles>Andorra</ingles><espanhol>Andorra</espanhol></lista_paises_bing><lista_paises_bing><codigo>pt-ao</codigo><portugues>Angola</portugues><ingles>Angola</ingles><espanhol>Angola</espanhol></lista_paises_bing><lista_paises_bing><codigo>en-ai</codigo><portugues>Anguila</portugues><ingles>Anguilla</ingles><espanhol>Anguila</espanhol></lista_paises_bing><lista_paises_bing><codigo>en-ag</codigo><portugues>Antígua e Barbuda</portugues><ingles>Antigua and Barbuda</ingles><espanhol>Antigua y Barbuda</espanhol></lista_paises_bing><lista_paises_bing><codigo>ar-sa</codigo><portugues>Arábia Saudita</portugues><ingles>Saudi Arabia</ingles><espanhol>Arabia Saudí</espanhol></lista_paises_bing><lista_paises_bing><codigo>ar-dz</codigo><portugues>Argélia</portugues><ingles>Algeria</ingles><espanhol>Argelia</espanhol></lista_paises_bing><lista_paises_bing><codigo>es-ar</codigo><portugues>Argentina</portugues><ingles>Argentina</ingles><espanhol>Argentina</espanhol></lista_paises_bing><lista_paises_bing><codigo>hy-am</codigo><portugues>Armênia</portugues><ingles>Armenia</ingles><espanhol>Armenia</espanhol></lista_paises_bing><lista_paises_bing><codigo>nl-aw</codigo><portugues>Aruba</portugues><ingles>Aruba</ingles><espanhol>Aruba</espanhol></lista_paises_bing><lista_paises_bing><codigo>en-au</codigo><portugues>Austrália</portugues><ingles>Australia</ingles><espanhol>Australia</espanhol></lista_paises_bing><lista_paises_bing><codigo>de-at</codigo><portugues>Áustria</portugues><ingles>Austria</ingles><espanhol>Austria</espanhol></lista_paises_bing><lista_paises_bing><codigo>ar-ps</codigo><portugues>Autoridade Palestina</portugues><ingles>Palestinian Authority</ingles><espanhol>Autoridad Palestina</espanhol></lista_paises_bing><lista_paises_bing><codigo>az-latn-az</codigo><portugues>Azerbaijão</portugues><ingles>Azerbaijan</ingles><espanhol>Azerbaiyán</espanhol></lista_paises_bing><lista_paises_bing><codigo>en-bs</codigo><portugues>Bahamas</portugues><ingles>Bahamas</ingles><espanhol>Bahamas</espanhol></lista_paises_bing><lista_paises_bing><codigo>ar-bh</codigo><portugues>Bahrein</portugues><ingles>Bahrain</ingles><espanhol>Baréin</espanhol></lista_paises_bing><lista_paises_bing><codigo>bn-bd</codigo><portugues>Bangladesh</portugues><ingles>Bangladesh</ingles><espanhol>Bangladés</espanhol></lista_paises_bing><lista_paises_bing><codigo>en-bb</codigo><portugues>Barbados</portugues><ingles>Barbados</ingles><espanhol>Barbados</espanhol></lista_paises_bing><lista_paises_bing><codigo>be-by</codigo><portugues>Belarus</portugues><ingles>Belarus</ingles><espanhol>Belarús</espanhol></lista_paises_bing><lista_paises_bing><codigo>fr-be</codigo><portugues>Bélgica - Francês</portugues><ingles>Belgium - French</ingles><espanhol>Bélgica - Francés</espanhol></lista_paises_bing><lista_paises_bing><codigo>nl-be</codigo><portugues>Bélgica - Holandês</portugues><ingles>Belgium - Dutch</ingles><espanhol>Bélgica - Neerlandés</espanhol></lista_paises_bing><lista_paises_bing><codigo>en-bz</codigo><portugues>Belize</portugues><ingles>Belize</ingles><espanhol>Belice</espanhol></lista_paises_bing><lista_paises_bing><codigo>fr-bj</codigo><portugues>Benin</portugues><ingles>Benin</ingles><espanhol>Benín</espanhol></lista_paises_bing><lista_paises_bing><codigo>en-bm</codigo><portugues>Bermudas</portugues><ingles>Bermuda</ingles><espanhol>Bermudas</espanhol></lista_paises_bing><lista_paises_bing><codigo>es-bo</codigo><portugues>Bolívia</portugues><ingles>Bolivia</ingles><espanhol>Bolivia</espanhol></lista_paises_bing><lista_paises_bing><codigo>bs-latn-ba</codigo><portugues>Bósnia e Herzegovina</portugues><ingles>Bosnia &amp; Herzegovina</ingles><espanhol>Bosnia y Herzegovina</espanhol></lista_paises_bing><lista_paises_bing><codigo>en-bw</codigo><portugues>Botsuana</portugues><ingles>Botswana</ingles><espanhol>Botsuana</espanhol></lista_paises_bing><lista_paises_bing><codigo>pt-br</codigo><portugues>Brasil</portugues><ingles>Brazil</ingles><espanhol>Brasil</espanhol></lista_paises_bing><lista_paises_bing><codigo>ms-bn</codigo><portugues>Brunei</portugues><ingles>Brunei</ingles><espanhol>Brunéi</espanhol></lista_paises_bing><lista_paises_bing><codigo>bg-bg</codigo><portugues>Bulgária</portugues><ingles>Bulgaria</ingles><espanhol>Bulgaria</espanhol></lista_paises_bing><lista_paises_bing><codigo>fr-bf</codigo><portugues>Burquina Faso</portugues><ingles>Burkina Faso</ingles><espanhol>Burkina Faso</espanhol></lista_paises_bing><lista_paises_bing><codigo>fr-bi</codigo><portugues>Burundi</portugues><ingles>Burundi</ingles><espanhol>Burundi</espanhol></lista_paises_bing><lista_paises_bing><codigo>bo-bt</codigo><portugues>Butão</portugues><ingles>Bhutan</ingles><espanhol>Bután</espanhol></lista_paises_bing><lista_paises_bing><codigo>pt-cv</codigo><portugues>Cabo Verde</portugues><ingles>Cabo Verde</ingles><espanhol>Cabo Verde</espanhol></lista_paises_bing><lista_paises_bing><codigo>fr-cm</codigo><portugues>Camarões</portugues><ingles>Cameroon</ingles><espanhol>Camerún</espanhol></lista_paises_bing><lista_paises_bing><codigo>km-kh</codigo><portugues>Camboja</portugues><ingles>Cambodia</ingles><espanhol>Camboya</espanhol></lista_paises_bing><lista_paises_bing><codigo>fr-ca</codigo><portugues>Canadá - Francês</portugues><ingles>Canada - French</ingles><espanhol>Canadá - Francés</espanhol></lista_paises_bing><lista_paises_bing><codigo>en-ca</codigo><portugues>Canadá - Inglês</portugues><ingles>Canada - English</ingles><espanhol>Canadá - Inglés</espanhol></lista_paises_bing><lista_paises_bing><codigo>ar-qa</codigo><portugues>Catar</portugues><ingles>Qatar</ingles><espanhol>Catar</espanhol></lista_paises_bing><lista_paises_bing><codigo>kk-kz</codigo><portugues>Cazaquistão</portugues><ingles>Kazakhstan</ingles><espanhol>Kazajistán</espanhol></lista_paises_bing><lista_paises_bing><codigo>fr-td</codigo><portugues>Chade</portugues><ingles>Chad</ingles><espanhol>Chad</espanhol></lista_paises_bing><lista_paises_bing><codigo>es-cl</codigo><portugues>Chile</portugues><ingles>Chile</ingles><espanhol>Chile</espanhol></lista_paises_bing><lista_paises_bing><codigo>zh-cn</codigo><portugues>China</portugues><ingles>China</ingles><espanhol>China</espanhol></lista_paises_bing><lista_paises_bing><codigo>en-cy</codigo><portugues>Chipre</portugues><ingles>Cyprus</ingles><espanhol>Chipre</espanhol></lista_paises_bing><lista_paises_bing><codigo>it-va</codigo><portugues>Cidade do Vaticano</portugues><ingles>Vatican City</ingles><espanhol>Ciudad del Vaticano</espanhol></lista_paises_bing><lista_paises_bing><codigo>es-co</codigo><portugues>Colômbia</portugues><ingles>Colombia</ingles><espanhol>Colombia</espanhol></lista_paises_bing><lista_paises_bing><codigo>fr-km</codigo><portugues>Comores</portugues><ingles>Comoros</ingles><espanhol>Comoras</espanhol></lista_paises_bing><lista_paises_bing><codigo>fr-cg</codigo><portugues>Congo</portugues><ingles>Congo</ingles><espanhol>Congo</espanhol></lista_paises_bing><lista_paises_bing><codigo>fr-cd</codigo><portugues>Congo (RDC)</portugues><ingles>Congo (DRC)</ingles><espanhol>Congo (RDC)</espanhol></lista_paises_bing><lista_paises_bing><codigo>ko-kr</codigo><portugues>Coreia do Sul</portugues><ingles>Korea</ingles><espanhol>Corea del Sur</espanhol></lista_paises_bing><lista_paises_bing><codigo>es-cr</codigo><portugues>Costa Rica</portugues><ingles>Costa Rica</ingles><espanhol>Costa Rica</espanhol></lista_paises_bing><lista_paises_bing><codigo>fr-ci</codigo><portugues>Côte d'Ivoire</portugues><ingles>Côte d'Ivoire</ingles><espanhol>Côte d'Ivoire</espanhol></lista_paises_bing><lista_paises_bing><codigo>hr-hr</codigo><portugues>Croácia</portugues><ingles>Croatia</ingles><espanhol>Croacia</espanhol></lista_paises_bing><lista_paises_bing><codigo>nl-cw</codigo><portugues>Curaçao</portugues><ingles>Curaçao</ingles><espanhol>Curazao</espanhol></lista_paises_bing><lista_paises_bing><codigo>da-dk</codigo><portugues>Dinamarca</portugues><ingles>Denmark</ingles><espanhol>Dinamarca</espanhol></lista_paises_bing><lista_paises_bing><codigo>fr-dj</codigo><portugues>Djibuti</portugues><ingles>Djibouti</ingles><espanhol>Yibuti</espanhol></lista_paises_bing><lista_paises_bing><codigo>en-dm</codigo><portugues>Dominica</portugues><ingles>Dominica</ingles><espanhol>Dominica</espanhol></lista_paises_bing><lista_paises_bing><codigo>ar-eg</codigo><portugues>Egito</portugues><ingles>Egypt</ingles><espanhol>Egipto</espanhol></lista_paises_bing><lista_paises_bing><codigo>es-sv</codigo><portugues>El Salvador</portugues><ingles>El Salvador</ingles><espanhol>El Salvador</espanhol></lista_paises_bing><lista_paises_bing><codigo>ar-ae</codigo><portugues>Emirados Árabes Unidos</portugues><ingles>United Arab Emirates</ingles><espanhol>Emiratos Árabes Unidos</espanhol></lista_paises_bing><lista_paises_bing><codigo>es-ec</codigo><portugues>Equador</portugues><ingles>Ecuador</ingles><espanhol>Ecuador</espanhol></lista_paises_bing><lista_paises_bing><codigo>ti-er</codigo><portugues>Eritreia</portugues><ingles>Eritrea</ingles><espanhol>Eritrea</espanhol></lista_paises_bing><lista_paises_bing><codigo>sk-sk</codigo><portugues>Eslováquia</portugues><ingles>Slovakia</ingles><espanhol>Eslovaquia</espanhol></lista_paises_bing><lista_paises_bing><codigo>sl-si</codigo><portugues>Eslovênia</portugues><ingles>Slovenia</ingles><espanhol>Eslovenia</espanhol></lista_paises_bing><lista_paises_bing><codigo>es-es</codigo><portugues>Espanha</portugues><ingles>Spain</ingles><espanhol>España</espanhol></lista_paises_bing><lista_paises_bing><codigo>en-sz</codigo><portugues>Essuatíni</portugues><ingles>Eswatini</ingles><espanhol>Suazilandia</espanhol></lista_paises_bing><lista_paises_bing><codigo>es-us</codigo><portugues>Estados Unidos - Espanhol</portugues><ingles>United States - Spanish</ingles><espanhol>Estados Unidos - Español</espanhol></lista_paises_bing><lista_paises_bing><codigo>en-us</codigo><portugues>Estados Unidos - Inglês</portugues><ingles>United States - English</ingles><espanhol>Estados Unidos - Inglés</espanhol></lista_paises_bing><lista_paises_bing><codigo>et-ee</codigo><portugues>Estônia</portugues><ingles>Estonia</ingles><espanhol>Estonia</espanhol></lista_paises_bing><lista_paises_bing><codigo>am-et</codigo><portugues>Etiópia</portugues><ingles>Ethiopia</ingles><espanhol>Etiopía</espanhol></lista_paises_bing><lista_paises_bing><codigo>en-fj</codigo><portugues>Fiji</portugues><ingles>Fiji</ingles><espanhol>Fiyi</espanhol></lista_paises_bing><lista_paises_bing><codigo>en-ph</codigo><portugues>Filipinas</portugues><ingles>Philippines</ingles><espanhol>Filipinas</espanhol></lista_paises_bing><lista_paises_bing><codigo>fi-fi</codigo><portugues>Finlândia</portugues><ingles>Finland</ingles><espanhol>Finlandia</espanhol></lista_paises_bing><lista_paises_bing><codigo>fr-fr</codigo><portugues>França</portugues><ingles>France</ingles><espanhol>Francia</espanhol></lista_paises_bing><lista_paises_bing><codigo>fr-ga</codigo><portugues>Gabão</portugues><ingles>Gabon</ingles><espanhol>Gabón</espanhol></lista_paises_bing><lista_paises_bing><codigo>en-gm</codigo><portugues>Gâmbia</portugues><ingles>Gambia</ingles><espanhol>Gambia</espanhol></lista_paises_bing><lista_paises_bing><codigo>en-gh</codigo><portugues>Gana</portugues><ingles>Ghana</ingles><espanhol>Ghana</espanhol></lista_paises_bing><lista_paises_bing><codigo>ka-ge</codigo><portugues>Geórgia</portugues><ingles>Georgia</ingles><espanhol>Georgia</espanhol></lista_paises_bing><lista_paises_bing><codigo>en-gi</codigo><portugues>Gibraltar</portugues><ingles>Gibraltar</ingles><espanhol>Gibraltar</espanhol></lista_paises_bing><lista_paises_bing><codigo>en-gd</codigo><portugues>Granada</portugues><ingles>Grenada</ingles><espanhol>Granada</espanhol></lista_paises_bing><lista_paises_bing><codigo>el-gr</codigo><portugues>Grécia</portugues><ingles>Greece</ingles><espanhol>Grecia</espanhol></lista_paises_bing><lista_paises_bing><codigo>kl-gl</codigo><portugues>Groenlândia</portugues><ingles>Greenland</ingles><espanhol>Groenlandia</espanhol></lista_paises_bing><lista_paises_bing><codigo>fr-gp</codigo><portugues>Guadalupe</portugues><ingles>Guadeloupe</ingles><espanhol>Guadalupe</espanhol></lista_paises_bing><lista_paises_bing><codigo>en-gu</codigo><portugues>Guam</portugues><ingles>Guam</ingles><espanhol>Guam</espanhol></lista_paises_bing><lista_paises_bing><codigo>es-gt</codigo><portugues>Guatemala</portugues><ingles>Guatemala</ingles><espanhol>Guatemala</espanhol></lista_paises_bing><lista_paises_bing><codigo>en-gg</codigo><portugues>Guernsey</portugues><ingles>Guernsey</ingles><espanhol>Guernesey</espanhol></lista_paises_bing><lista_paises_bing><codigo>en-gy</codigo><portugues>Guiana</portugues><ingles>Guyana</ingles><espanhol>Guyana</espanhol></lista_paises_bing><lista_paises_bing><codigo>fr-gf</codigo><portugues>Guiana Francesa</portugues><ingles>French Guiana</ingles><espanhol>Guayana Francesa</espanhol></lista_paises_bing><lista_paises_bing><codigo>fr-gn</codigo><portugues>Guiné</portugues><ingles>Guinea</ingles><espanhol>Guinea</espanhol></lista_paises_bing><lista_paises_bing><codigo>es-gq</codigo><portugues>Guiné Equatorial</portugues><ingles>Equatorial Guinea</ingles><espanhol>Guinea Ecuatorial</espanhol></lista_paises_bing><lista_paises_bing><codigo>pt-gw</codigo><portugues>Guiné-Bissau</portugues><ingles>Guinea-Bissau</ingles><espanhol>Guinea-Bisáu</espanhol></lista_paises_bing><lista_paises_bing><codigo>fr-ht</codigo><portugues>Haiti</portugues><ingles>Haiti</ingles><espanhol>Haití</espanhol></lista_paises_bing><lista_paises_bing><codigo>es-hn</codigo><portugues>Honduras</portugues><ingles>Honduras</ingles><espanhol>Honduras</espanhol></lista_paises_bing><lista_paises_bing><codigo>hu-hu</codigo><portugues>Hungria</portugues><ingles>Hungary</ingles><espanhol>Hungría</espanhol></lista_paises_bing><lista_paises_bing><codigo>ar-ye</codigo><portugues>Iêmen</portugues><ingles>Yemen</ingles><espanhol>Yemen</espanhol></lista_paises_bing><lista_paises_bing><codigo>en-cx</codigo><portugues>Ilha Christmas</portugues><ingles>Christmas Island</ingles><espanhol>Isla Christmas</espanhol></lista_paises_bing><lista_paises_bing><codigo>en-nf</codigo><portugues>Ilha Norfolk</portugues><ingles>Norfolk Island</ingles><espanhol>Isla Norfolk</espanhol></lista_paises_bing><lista_paises_bing><codigo>en-ky</codigo><portugues>Ilhas Cayman</portugues><ingles>Cayman Islands</ingles><espanhol>Islas Caimán</espanhol></lista_paises_bing><lista_paises_bing><codigo>en-cc</codigo><portugues>Ilhas Cocos (Keeling)</portugues><ingles>Cocos (Keeling) Islands</ingles><espanhol>Islas Cocos</espanhol></lista_paises_bing><lista_paises_bing><codigo>en-ck</codigo><portugues>Ilhas Cook</portugues><ingles>Cook Islands</ingles><espanhol>Islas Cook</espanhol></lista_paises_bing><lista_paises_bing><codigo>fo-fo</codigo><portugues>Ilhas Faroe</portugues><ingles>Faroe Islands</ingles><espanhol>Islas Feroe</espanhol></lista_paises_bing><lista_paises_bing><codigo>en-fk</codigo><portugues>Ilhas Malvinas</portugues><ingles>Falkland Islands</ingles><espanhol>Islas Malvinas</espanhol></lista_paises_bing><lista_paises_bing><codigo>en-mp</codigo><portugues>Ilhas Marianas do Norte</portugues><ingles>Northern Mariana Islands</ingles><espanhol>Islas Marianas del Norte</espanhol></lista_paises_bing><lista_paises_bing><codigo>en-mh</codigo><portugues>Ilhas Marshall</portugues><ingles>Marshall Islands</ingles><espanhol>Islas Marshall</espanhol></lista_paises_bing><lista_paises_bing><codigo>en-pn</codigo><portugues>Ilhas Pitcairn</portugues><ingles>Pitcairn Islands</ingles><espanhol>Islas Pitcairn</espanhol></lista_paises_bing><lista_paises_bing><codigo>en-sb</codigo><portugues>Ilhas Salomão</portugues><ingles>Solomon Islands</ingles><espanhol>Islas Salomón</espanhol></lista_paises_bing><lista_paises_bing><codigo>en-tc</codigo><portugues>Ilhas Turcas e Caicos</portugues><ingles>Turks and Caicos Islands</ingles><espanhol>Islas Turcas y Caicos</espanhol></lista_paises_bing><lista_paises_bing><codigo>en-vi</codigo><portugues>Ilhas Virgens Americanas</portugues><ingles>U.S. Virgin Islands</ingles><espanhol>Islas Vírgenes de EE. UU.</espanhol></lista_paises_bing><lista_paises_bing><codigo>en-vg</codigo><portugues>Ilhas Virgens Britânicas</portugues><ingles>British Virgin Islands</ingles><espanhol>Islas Vírgenes Británicas</espanhol></lista_paises_bing><lista_paises_bing><codigo>en-in</codigo><portugues>Índia</portugues><ingles>India</ingles><espanhol>India</espanhol></lista_paises_bing><lista_paises_bing><codigo>id-id</codigo><portugues>Indonésia</portugues><ingles>Indonesia</ingles><espanhol>Indonesia</espanhol></lista_paises_bing><lista_paises_bing><codigo>fa-ir</codigo><portugues>Irã</portugues><ingles>Iran</ingles><espanhol>Irán</espanhol></lista_paises_bing><lista_paises_bing><codigo>ar-iq</codigo><portugues>Iraque</portugues><ingles>Iraq</ingles><espanhol>Irak</espanhol></lista_paises_bing><lista_paises_bing><codigo>en-ie</codigo><portugues>Irlanda</portugues><ingles>Ireland</ingles><espanhol>Irlanda</espanhol></lista_paises_bing><lista_paises_bing><codigo>is-is</codigo><portugues>Islândia</portugues><ingles>Iceland</ingles><espanhol>Islandia</espanhol></lista_paises_bing><lista_paises_bing><codigo>he-il</codigo><portugues>Israel</portugues><ingles>Israel</ingles><espanhol>Israel</espanhol></lista_paises_bing><lista_paises_bing><codigo>it-it</codigo><portugues>Itália</portugues><ingles>Italy</ingles><espanhol>Italia</espanhol></lista_paises_bing><lista_paises_bing><codigo>en-jm</codigo><portugues>Jamaica</portugues><ingles>Jamaica</ingles><espanhol>Jamaica</espanhol></lista_paises_bing><lista_paises_bing><codigo>ja-jp</codigo><portugues>Japão</portugues><ingles>Japan</ingles><espanhol>Japón</espanhol></lista_paises_bing><lista_paises_bing><codigo>en-je</codigo><portugues>Jersey</portugues><ingles>Jersey</ingles><espanhol>Jersey</espanhol></lista_paises_bing><lista_paises_bing><codigo>ar-jo</codigo><portugues>Jordânia</portugues><ingles>Jordan</ingles><espanhol>Jordania</espanhol></lista_paises_bing><lista_paises_bing><codigo>ar-kw</codigo><portugues>Kuwait</portugues><ingles>Kuwait</ingles><espanhol>Kuwait</espanhol></lista_paises_bing><lista_paises_bing><codigo>lo-la</codigo><portugues>Laos</portugues><ingles>Laos</ingles><espanhol>Laos</espanhol></lista_paises_bing><lista_paises_bing><codigo>en-ls</codigo><portugues>Lesoto</portugues><ingles>Lesotho</ingles><espanhol>Lesoto</espanhol></lista_paises_bing><lista_paises_bing><codigo>lv-lv</codigo><portugues>Letônia</portugues><ingles>Latvia</ingles><espanhol>Letonia</espanhol></lista_paises_bing><lista_paises_bing><codigo>ar-lb</codigo><portugues>Líbano</portugues><ingles>Lebanon</ingles><espanhol>Líbano</espanhol></lista_paises_bing><lista_paises_bing><codigo>en-lr</codigo><portugues>Libéria</portugues><ingles>Liberia</ingles><espanhol>Liberia</espanhol></lista_paises_bing><lista_paises_bing><codigo>ar-ly</codigo><portugues>Líbia</portugues><ingles>Libya</ingles><espanhol>Libia</espanhol></lista_paises_bing><lista_paises_bing><codigo>de-li</codigo><portugues>Liechtenstein</portugues><ingles>Liechtenstein</ingles><espanhol>Liechtenstein</espanhol></lista_paises_bing><lista_paises_bing><codigo>lt-lt</codigo><portugues>Lituânia</portugues><ingles>Lithuania</ingles><espanhol>Lituania</espanhol></lista_paises_bing><lista_paises_bing><codigo>fr-lu</codigo><portugues>Luxemburgo</portugues><ingles>Luxembourg</ingles><espanhol>Luxemburgo</espanhol></lista_paises_bing><lista_paises_bing><codigo>mk-mk</codigo><portugues>Macedônia do Norte</portugues><ingles>North Macedonia</ingles><espanhol>Macedonia del Norte</espanhol></lista_paises_bing><lista_paises_bing><codigo>fr-mg</codigo><portugues>Madagascar</portugues><ingles>Madagascar</ingles><espanhol>Madagascar</espanhol></lista_paises_bing><lista_paises_bing><codigo>ms-my</codigo><portugues>Malásia</portugues><ingles>Malaysia</ingles><espanhol>Malasia</espanhol></lista_paises_bing><lista_paises_bing><codigo>en-mw</codigo><portugues>Malaui</portugues><ingles>Malawi</ingles><espanhol>Malaui</espanhol></lista_paises_bing><lista_paises_bing><codigo>dv-mv</codigo><portugues>Maldivas</portugues><ingles>Maldives</ingles><espanhol>Maldivas</espanhol></lista_paises_bing><lista_paises_bing><codigo>fr-ml</codigo><portugues>Mali</portugues><ingles>Mali</ingles><espanhol>Mali</espanhol></lista_paises_bing><lista_paises_bing><codigo>mt-mt</codigo><portugues>Malta</portugues><ingles>Malta</ingles><espanhol>Malta</espanhol></lista_paises_bing><lista_paises_bing><codigo>ar-ma</codigo><portugues>Marrocos</portugues><ingles>Morocco</ingles><espanhol>Marruecos</espanhol></lista_paises_bing><lista_paises_bing><codigo>fr-mq</codigo><portugues>Martinica</portugues><ingles>Martinique</ingles><espanhol>Martinica</espanhol></lista_paises_bing><lista_paises_bing><codigo>en-mu</codigo><portugues>Maurício</portugues><ingles>Mauritius</ingles><espanhol>Mauricio</espanhol></lista_paises_bing><lista_paises_bing><codigo>ar-mr</codigo><portugues>Mauritânia</portugues><ingles>Mauritania</ingles><espanhol>Mauritania</espanhol></lista_paises_bing><lista_paises_bing><codigo>fr-yt</codigo><portugues>Mayotte</portugues><ingles>Mayotte</ingles><espanhol>Mayotte</espanhol></lista_paises_bing><lista_paises_bing><codigo>es-mx</codigo><portugues>México</portugues><ingles>Mexico</ingles><espanhol>México</espanhol></lista_paises_bing><lista_paises_bing><codigo>en-fm</codigo><portugues>Micronésia</portugues><ingles>Micronesia</ingles><espanhol>Micronesia</espanhol></lista_paises_bing><lista_paises_bing><codigo>pt-mz</codigo><portugues>Moçambique</portugues><ingles>Mozambique</ingles><espanhol>Mozambique</espanhol></lista_paises_bing><lista_paises_bing><codigo>ro-md</codigo><portugues>Moldova</portugues><ingles>Moldova</ingles><espanhol>Moldova</espanhol></lista_paises_bing><lista_paises_bing><codigo>fr-mc</codigo><portugues>Mônaco</portugues><ingles>Monaco</ingles><espanhol>Mónaco</espanhol></lista_paises_bing><lista_paises_bing><codigo>mn-mn</codigo><portugues>Mongólia</portugues><ingles>Mongolia</ingles><espanhol>Mongolia</espanhol></lista_paises_bing><lista_paises_bing><codigo>sr-me</codigo><portugues>Montenegro</portugues><ingles>Montenegro</ingles><espanhol>Montenegro</espanhol></lista_paises_bing><lista_paises_bing><codigo>en-ms</codigo><portugues>Montserrat</portugues><ingles>Montserrat</ingles><espanhol>Montserrat</espanhol></lista_paises_bing><lista_paises_bing><codigo>en-mm</codigo><portugues>Myanmar</portugues><ingles>Myanmar</ingles><espanhol>Myanmar</espanhol></lista_paises_bing><lista_paises_bing><codigo>af-na</codigo><portugues>Namíbia</portugues><ingles>Namibia</ingles><espanhol>Namibia</espanhol></lista_paises_bing><lista_paises_bing><codigo>en-nr</codigo><portugues>Nauru</portugues><ingles>Nauru</ingles><espanhol>Nauru</espanhol></lista_paises_bing><lista_paises_bing><codigo>ne-np</codigo><portugues>Nepal</portugues><ingles>Nepal</ingles><espanhol>Nepal</espanhol></lista_paises_bing><lista_paises_bing><codigo>es-ni</codigo><portugues>Nicarágua</portugues><ingles>Nicaragua</ingles><espanhol>Nicaragua</espanhol></lista_paises_bing><lista_paises_bing><codigo>fr-ne</codigo><portugues>Níger</portugues><ingles>Niger</ingles><espanhol>Níger</espanhol></lista_paises_bing><lista_paises_bing><codigo>en-ng</codigo><portugues>Nigéria</portugues><ingles>Nigeria</ingles><espanhol>Nigeria</espanhol></lista_paises_bing><lista_paises_bing><codigo>en-nu</codigo><portugues>Niue</portugues><ingles>Niue</ingles><espanhol>Niue</espanhol></lista_paises_bing><lista_paises_bing><codigo>nb-no</codigo><portugues>Noruega</portugues><ingles>Norway</ingles><espanhol>Noruega</espanhol></lista_paises_bing><lista_paises_bing><codigo>fr-nc</codigo><portugues>Nova Caledônia</portugues><ingles>New Caledonia</ingles><espanhol>Nueva Caledonia</espanhol></lista_paises_bing><lista_paises_bing><codigo>en-nz</codigo><portugues>Nova Zelândia</portugues><ingles>New Zealand</ingles><espanhol>Nueva Zelanda</espanhol></lista_paises_bing><lista_paises_bing><codigo>ar-om</codigo><portugues>Omã</portugues><ingles>Oman</ingles><espanhol>Omán</espanhol></lista_paises_bing><lista_paises_bing><codigo>nl-nl</codigo><portugues>Países Baixos</portugues><ingles>Netherlands</ingles><espanhol>Países Bajos</espanhol></lista_paises_bing><lista_paises_bing><codigo>en-pw</codigo><portugues>Palau</portugues><ingles>Palau</ingles><espanhol>Palaos</espanhol></lista_paises_bing><lista_paises_bing><codigo>es-pa</codigo><portugues>Panamá</portugues><ingles>Panama</ingles><espanhol>Panamá</espanhol></lista_paises_bing><lista_paises_bing><codigo>en-pg</codigo><portugues>Papua-Nova Guiné</portugues><ingles>Papua New Guinea</ingles><espanhol>Papúa Nueva Guinea</espanhol></lista_paises_bing><lista_paises_bing><codigo>ur-pk</codigo><portugues>Paquistão</portugues><ingles>Pakistan</ingles><espanhol>Pakistán</espanhol></lista_paises_bing><lista_paises_bing><codigo>es-py</codigo><portugues>Paraguai</portugues><ingles>Paraguay</ingles><espanhol>Paraguay</espanhol></lista_paises_bing><lista_paises_bing><codigo>es-pe</codigo><portugues>Peru</portugues><ingles>Peru</ingles><espanhol>Perú</espanhol></lista_paises_bing><lista_paises_bing><codigo>fr-pf</codigo><portugues>Polinésia Francesa</portugues><ingles>French Polynesia</ingles><espanhol>Polinesia Francesa</espanhol></lista_paises_bing><lista_paises_bing><codigo>pl-pl</codigo><portugues>Polônia</portugues><ingles>Poland</ingles><espanhol>Polonia</espanhol></lista_paises_bing><lista_paises_bing><codigo>es-pr</codigo><portugues>Porto Rico</portugues><ingles>Puerto Rico</ingles><espanhol>Puerto Rico</espanhol></lista_paises_bing><lista_paises_bing><codigo>pt-pt</codigo><portugues>Portugal</portugues><ingles>Portugal</ingles><espanhol>Portugal</espanhol></lista_paises_bing><lista_paises_bing><codigo>sw-ke</codigo><portugues>Quênia</portugues><ingles>Kenya</ingles><espanhol>Kenia</espanhol></lista_paises_bing><lista_paises_bing><codigo>ky-kg</codigo><portugues>Quirguistão</portugues><ingles>Kyrgyzstan</ingles><espanhol>Kirguistán</espanhol></lista_paises_bing><lista_paises_bing><codigo>en-ki</codigo><portugues>Quiribati</portugues><ingles>Kiribati</ingles><espanhol>Kiribati</espanhol></lista_paises_bing><lista_paises_bing><codigo>zh-hk</codigo><portugues>RAE de Hong Kong</portugues><ingles>Hong Kong SAR</ingles><espanhol>RAE de Hong Kong</espanhol></lista_paises_bing><lista_paises_bing><codigo>zh-mo</codigo><portugues>RAE de Macau</portugues><ingles>Macao SAR</ingles><espanhol>RAE de Macao</espanhol></lista_paises_bing><lista_paises_bing><codigo>en-gb</codigo><portugues>Reino Unido</portugues><ingles>United Kingdom</ingles><espanhol>Reino Unido</espanhol></lista_paises_bing><lista_paises_bing><codigo>fr-cf</codigo><portugues>República Centro-Africana</portugues><ingles>Central African Republic</ingles><espanhol>República Centroafricana</espanhol></lista_paises_bing><lista_paises_bing><codigo>es-do</codigo><portugues>República Dominicana</portugues><ingles>Dominican Republic</ingles><espanhol>República Dominicana</espanhol></lista_paises_bing><lista_paises_bing><codigo>fr-re</codigo><portugues>Reunião</portugues><ingles>Réunion</ingles><espanhol>Reunión</espanhol></lista_paises_bing><lista_paises_bing><codigo>ro-ro</codigo><portugues>Romênia</portugues><ingles>Romania</ingles><espanhol>Rumania</espanhol></lista_paises_bing><lista_paises_bing><codigo>rw-rw</codigo><portugues>Ruanda</portugues><ingles>Rwanda</ingles><espanhol>Ruanda</espanhol></lista_paises_bing><lista_paises_bing><codigo>ru-ru</codigo><portugues>Rússia</portugues><ingles>Russia</ingles><espanhol>Rusia</espanhol></lista_paises_bing><lista_paises_bing><codigo>fr-mf</codigo><portugues>Saint Martin</portugues><ingles>Saint Martin</ingles><espanhol>San Martín</espanhol></lista_paises_bing><lista_paises_bing><codigo>en-ws</codigo><portugues>Samoa</portugues><ingles>Samoa</ingles><espanhol>Samoa</espanhol></lista_paises_bing><lista_paises_bing><codigo>en-as</codigo><portugues>Samoa Americana</portugues><ingles>American Samoa</ingles><espanhol>Samoa Americana</espanhol></lista_paises_bing><lista_paises_bing><codigo>it-sm</codigo><portugues>San Marino</portugues><ingles>San Marino</ingles><espanhol>San Marino</espanhol></lista_paises_bing><lista_paises_bing><codigo>en-sh</codigo><portugues>Santa Helena, Ascensão e Tristão da Cunha</portugues><ingles>St Helena, Ascension, Tristan da Cunha</ingles><espanhol>Santa Elena, Ascensión y Tristán da Cunha</espanhol></lista_paises_bing><lista_paises_bing><codigo>en-lc</codigo><portugues>Santa Lúcia</portugues><ingles>Saint Lucia</ingles><espanhol>Santa Lucía</espanhol></lista_paises_bing><lista_paises_bing><codigo>fr-bl</codigo><portugues>São Bartolomeu</portugues><ingles>Saint Barthélemy</ingles><espanhol>San Bartolomé</espanhol></lista_paises_bing><lista_paises_bing><codigo>en-kn</codigo><portugues>São Cristóvão e Névis</portugues><ingles>Saint Kitts and Nevis</ingles><espanhol>San Cristóbal y Nieves</espanhol></lista_paises_bing><lista_paises_bing><codigo>fr-pm</codigo><portugues>São Pedro e Miquelão</portugues><ingles>Saint Pierre and Miquelon</ingles><espanhol>San Pedro y Miquelón</espanhol></lista_paises_bing><lista_paises_bing><codigo>pt-st</codigo><portugues>São Tomé e Príncipe</portugues><ingles>São Tomé &amp; Príncipe</ingles><espanhol>Santo Tomé y Príncipe</espanhol></lista_paises_bing><lista_paises_bing><codigo>en-vc</codigo><portugues>São Vicente e Granadinas</portugues><ingles>Saint Vincent and the Grenadines</ingles><espanhol>San Vicente y las Granadinas</espanhol></lista_paises_bing><lista_paises_bing><codigo>en-sc</codigo><portugues>Seicheles</portugues><ingles>Seychelles</ingles><espanhol>Seychelles</espanhol></lista_paises_bing><lista_paises_bing><codigo>fr-sn</codigo><portugues>Senegal</portugues><ingles>Senegal</ingles><espanhol>Senegal</espanhol></lista_paises_bing><lista_paises_bing><codigo>en-sl</codigo><portugues>Serra Leoa</portugues><ingles>Sierra Leone</ingles><espanhol>Sierra Leona</espanhol></lista_paises_bing><lista_paises_bing><codigo>sr-latn-rs</codigo><portugues>Sérvia</portugues><ingles>Serbia</ingles><espanhol>Serbia</espanhol></lista_paises_bing><lista_paises_bing><codigo>en-sg</codigo><portugues>Singapura</portugues><ingles>Singapore</ingles><espanhol>Singapur</espanhol></lista_paises_bing><lista_paises_bing><codigo>nl-sx</codigo><portugues>Sint Maarten</portugues><ingles>Sint Maarten</ingles><espanhol>Sint Maarten</espanhol></lista_paises_bing><lista_paises_bing><codigo>ar-sy</codigo><portugues>Síria</portugues><ingles>Syria</ingles><espanhol>Siria</espanhol></lista_paises_bing><lista_paises_bing><codigo>so-so</codigo><portugues>Somália</portugues><ingles>Somalia</ingles><espanhol>Somalia</espanhol></lista_paises_bing><lista_paises_bing><codigo>si-lk</codigo><portugues>Sri Lanka</portugues><ingles>Sri Lanka</ingles><espanhol>Sri Lanka</espanhol></lista_paises_bing><lista_paises_bing><codigo>ar-sd</codigo><portugues>Sudão</portugues><ingles>Sudan</ingles><espanhol>Sudán</espanhol></lista_paises_bing><lista_paises_bing><codigo>en-ss</codigo><portugues>Sudão do Sul</portugues><ingles>South Sudan</ingles><espanhol>Sudán del Sur</espanhol></lista_paises_bing><lista_paises_bing><codigo>sv-se</codigo><portugues>Suécia</portugues><ingles>Sweden</ingles><espanhol>Suecia</espanhol></lista_paises_bing><lista_paises_bing><codigo>de-ch</codigo><portugues>Suíça - Alemão</portugues><ingles>Switzerland - German</ingles><espanhol>Suiza - Alemán</espanhol></lista_paises_bing><lista_paises_bing><codigo>fr-ch</codigo><portugues>Suíça - Francês</portugues><ingles>Switzerland - French</ingles><espanhol>Suiza - Francés</espanhol></lista_paises_bing><lista_paises_bing><codigo>nl-sr</codigo><portugues>Suriname</portugues><ingles>Suriname</ingles><espanhol>Surinam</espanhol></lista_paises_bing><lista_paises_bing><codigo>tg-cyrl-tj</codigo><portugues>Tadjiquistão</portugues><ingles>Tajikistan</ingles><espanhol>Tayikistán</espanhol></lista_paises_bing><lista_paises_bing><codigo>th-th</codigo><portugues>Tailândia</portugues><ingles>Thailand</ingles><espanhol>Tailandia</espanhol></lista_paises_bing><lista_paises_bing><codigo>zh-tw</codigo><portugues>Taiwan</portugues><ingles>Taiwan</ingles><espanhol>Taiwán</espanhol></lista_paises_bing><lista_paises_bing><codigo>en-tz</codigo><portugues>Tanzânia</portugues><ingles>Tanzania</ingles><espanhol>Tanzania</espanhol></lista_paises_bing><lista_paises_bing><codigo>cs-cz</codigo><portugues>Tchéquia</portugues><ingles>Czechia</ingles><espanhol>Chequia</espanhol></lista_paises_bing><lista_paises_bing><codigo>fr-tg</codigo><portugues>Togo</portugues><ingles>Togo</ingles><espanhol>Togo</espanhol></lista_paises_bing><lista_paises_bing><codigo>en-tk</codigo><portugues>Tokelau</portugues><ingles>Tokelau</ingles><espanhol>Tokelau</espanhol></lista_paises_bing><lista_paises_bing><codigo>en-to</codigo><portugues>Tonga</portugues><ingles>Tonga</ingles><espanhol>Tonga</espanhol></lista_paises_bing><lista_paises_bing><codigo>en-tt</codigo><portugues>Trinidad e Tobago</portugues><ingles>Trinidad and Tobago</ingles><espanhol>Trinidad y Tobago</espanhol></lista_paises_bing><lista_paises_bing><codigo>ar-tn</codigo><portugues>Tunísia</portugues><ingles>Tunisia</ingles><espanhol>Túnez</espanhol></lista_paises_bing><lista_paises_bing><codigo>tk-tm</codigo><portugues>Turcomenistão</portugues><ingles>Turkmenistan</ingles><espanhol>Turkmenistán</espanhol></lista_paises_bing><lista_paises_bing><codigo>tr-tr</codigo><portugues>Turquia</portugues><ingles>Turkey</ingles><espanhol>Turquía</espanhol></lista_paises_bing><lista_paises_bing><codigo>en-tv</codigo><portugues>Tuvalu</portugues><ingles>Tuvalu</ingles><espanhol>Tuvalu</espanhol></lista_paises_bing><lista_paises_bing><codigo>uk-ua</codigo><portugues>Ucrânia</portugues><ingles>Ukraine</ingles><espanhol>Ucrania</espanhol></lista_paises_bing><lista_paises_bing><codigo>en-ug</codigo><portugues>Uganda</portugues><ingles>Uganda</ingles><espanhol>Uganda</espanhol></lista_paises_bing><lista_paises_bing><codigo>es-uy</codigo><portugues>Uruguai</portugues><ingles>Uruguay</ingles><espanhol>Uruguay</espanhol></lista_paises_bing><lista_paises_bing><codigo>uz-latn-uz</codigo><portugues>Uzbequistão</portugues><ingles>Uzbekistan</ingles><espanhol>Uzbekistán</espanhol></lista_paises_bing><lista_paises_bing><codigo>en-vu</codigo><portugues>Vanuatu</portugues><ingles>Vanuatu</ingles><espanhol>Vanuatu</espanhol></lista_paises_bing><lista_paises_bing><codigo>es-ve</codigo><portugues>Venezuela</portugues><ingles>Venezuela</ingles><espanhol>Venezuela</espanhol></lista_paises_bing><lista_paises_bing><codigo>vi-vn</codigo><portugues>Vietnã</portugues><ingles>Vietnam</ingles><espanhol>Vietnam</espanhol></lista_paises_bing><lista_paises_bing><codigo>fr-wf</codigo><portugues>Wallis e Futuna</portugues><ingles>Wallis and Futuna</ingles><espanhol>Wallis y Futuna</espanhol></lista_paises_bing><lista_paises_bing><codigo>en-zm</codigo><portugues>Zâmbia</portugues><ingles>Zambia</ingles><espanhol>Zambia</espanhol></lista_paises_bing><lista_paises_bing><codigo>en-zw</codigo><portugues>Zimbábue</portugues><ingles>Zimbabwe</ingles><espanhol>Zimbabue</espanhol></lista_paises_bing></dataroot>